molflux/__init__.py
molflux/py.typed
molflux/version.py
molflux/core/__init__.py
molflux/core/environment.py
molflux/core/io.py
molflux/core/models.py
molflux/core/scoring.py
molflux/core/tracking.py
molflux/core/typing.py
molflux/core/featurisation/__init__.py
molflux/core/featurisation/featurisation.py
molflux/core/featurisation/metadata.py
molflux/datasets/__init__.py
molflux/datasets/catalogue.py
molflux/datasets/exceptions.py
molflux/datasets/featurisation.py
molflux/datasets/filesystems.py
molflux/datasets/interfaces.py
molflux/datasets/io.py
molflux/datasets/load.py
molflux/datasets/naming.py
molflux/datasets/parsers.py
molflux/datasets/splitting.py
molflux/datasets/typing.py
molflux/datasets/utils.py
molflux/datasets/builders/__init__.py
molflux/datasets/builders/ani1x/README.md
molflux/datasets/builders/ani1x/__init__.py
molflux/datasets/builders/ani1x/ani1x.py
molflux/datasets/builders/ani2x/README.md
molflux/datasets/builders/ani2x/__init__.py
molflux/datasets/builders/ani2x/ani2x.py
molflux/datasets/builders/ani2x/ani2x_configs.py
molflux/datasets/builders/esol/README.md
molflux/datasets/builders/esol/__init__.py
molflux/datasets/builders/esol/esol.py
molflux/datasets/builders/gdb9/README.md
molflux/datasets/builders/gdb9/__init__.py
molflux/datasets/builders/gdb9/gdb9.py
molflux/datasets/builders/pcqm4m_v2/README.md
molflux/datasets/builders/pcqm4m_v2/__init__.py
molflux/datasets/builders/pcqm4m_v2/pcqm4m_v2.py
molflux/datasets/builders/spice/README.md
molflux/datasets/builders/spice/__init__.py
molflux/datasets/builders/spice/spice.py
molflux/datasets/builders/tdc/README.md
molflux/datasets/builders/tdc/__init__.py
molflux/datasets/builders/tdc/tdc_admet.py
molflux/features/__init__.py
molflux/features/bases.py
molflux/features/catalogue.py
molflux/features/config.py
molflux/features/errors.py
molflux/features/info.py
molflux/features/load.py
molflux/features/naming.py
molflux/features/parsers.py
molflux/features/representation.py
molflux-0.8.0.dist-info/LICENSE
molflux-0.8.0.dist-info/METADATA
molflux-0.8.0.dist-info/WHEEL
molflux-0.8.0.dist-info/entry_points.txt
molflux-0.8.0.dist-info/top_level.txt
molflux-0.8.0.dist-info/RECORD
