Metadata-Version: 2.1
Name: molflux
Version: 0.8.0
Summary: A foundational package for molecular predictive modelling
Author: Exscientia
Maintainer: Exscientia
Project-URL: documentation, https://exscientia.github.io/molflux/
Project-URL: repository, https://github.com/exscientia/molflux.git
Project-URL: issue-tracker, https://github.com/exscientia/molflux/issues
Project-URL: changelog, https://github.com/exscientia/molflux/src/main/CHANGELOG.md
Classifier: Development Status :: 4 - Beta
Classifier: Intended Audience :: Science/Research
Classifier: Natural Language :: English
Classifier: Operating System :: OS Independent
Classifier: Programming Language :: Python
Classifier: Programming Language :: Python :: 3 :: Only
Classifier: Programming Language :: Python :: 3.10
Classifier: Programming Language :: Python :: 3.11
Classifier: Typing :: Typed
Requires-Python: >=3.10
License-File: LICENSE
Requires-Dist: botocore >=1.28.16
Requires-Dist: boto3 >=1.34.0
Requires-Dist: cloudpathlib[s3]
Requires-Dist: colorama
Requires-Dist: datasets >=2.17.0
Requires-Dist: evaluate
Requires-Dist: fsspec >=2022.5.0
Requires-Dist: h5py
Requires-Dist: joblib
Requires-Dist: mergedeep
Requires-Dist: more-itertools
Requires-Dist: numpy <2.0.0
Requires-Dist: pandas
Requires-Dist: pyarrow >=11.0.0
Requires-Dist: pydantic <3,>=1.10.15
Requires-Dist: python-dateutil
Requires-Dist: pyyaml
Requires-Dist: requests
Requires-Dist: scikit-learn >=1.4.0
Requires-Dist: scipy >=1.7.0
Requires-Dist: tenacity
Requires-Dist: thefuzz[speedup]
Requires-Dist: tqdm
Requires-Dist: typing-extensions
Provides-Extra: catboost
Requires-Dist: catboost ; extra == 'catboost'
Requires-Dist: catboost >=1.2.0 ; (python_version >= "3.11") and extra == 'catboost'
Provides-Extra: dev
Requires-Dist: nox[uv] >=2024 ; extra == 'dev'
Requires-Dist: pre-commit ; extra == 'dev'
Provides-Extra: docs
Requires-Dist: sphinx !=5.1.0 ; extra == 'docs'
Requires-Dist: sphinx-sitemap ; extra == 'docs'
Requires-Dist: sphinx-inline-tabs ; extra == 'docs'
Requires-Dist: sphinx-book-theme ; extra == 'docs'
Requires-Dist: sphinx-design ; extra == 'docs'
Requires-Dist: sphinx-toolbox ; extra == 'docs'
Requires-Dist: sphinx-togglebutton ; extra == 'docs'
Requires-Dist: jupytext >=1.11.2 ; extra == 'docs'
Requires-Dist: myst-nb ; extra == 'docs'
Requires-Dist: ipywidgets ; extra == 'docs'
Requires-Dist: rdkit >=2023.9.1 ; extra == 'docs'
Requires-Dist: matplotlib ; extra == 'docs'
Requires-Dist: catboost >=1.2.0 ; extra == 'docs'
Requires-Dist: mapie ; extra == 'docs'
Provides-Extra: ensemble
Requires-Dist: scikit-learn >=1.2.1 ; extra == 'ensemble'
Provides-Extra: lightning
Requires-Dist: torch >=2.0 ; extra == 'lightning'
Requires-Dist: lightning >=2.1 ; extra == 'lightning'
Requires-Dist: class-resolver ; extra == 'lightning'
Provides-Extra: lightning_gp
Requires-Dist: torch >=2.0 ; extra == 'lightning_gp'
Requires-Dist: lightning >=2.1 ; extra == 'lightning_gp'
Requires-Dist: class-resolver ; extra == 'lightning_gp'
Requires-Dist: gpytorch ; extra == 'lightning_gp'
Provides-Extra: mapie
Requires-Dist: mapie ; extra == 'mapie'
Requires-Dist: scikit-learn >=1.2.1 ; extra == 'mapie'
Provides-Extra: openeye
Requires-Dist: openeye-toolkits ; extra == 'openeye'
Provides-Extra: pyod
Requires-Dist: combo ; extra == 'pyod'
Requires-Dist: pyod ; extra == 'pyod'
Provides-Extra: pystan
Requires-Dist: pystan >=3 ; extra == 'pystan'
Provides-Extra: rdkit
Requires-Dist: mhfp ; extra == 'rdkit'
Requires-Dist: rdkit >=2023.9.1 ; extra == 'rdkit'
Provides-Extra: sklearn
Requires-Dist: scikit-learn >=1.2.1 ; extra == 'sklearn'
Provides-Extra: tdc
Requires-Dist: PyTDC ; extra == 'tdc'
Provides-Extra: tests
Requires-Dist: coverage[toml] ; extra == 'tests'
Requires-Dist: moto[server] ; extra == 'tests'
Requires-Dist: pytest ; extra == 'tests'
Requires-Dist: mock ; extra == 'tests'
Provides-Extra: typing
Requires-Dist: mypy ; extra == 'typing'
Requires-Dist: types-pytz ; extra == 'typing'
Requires-Dist: types-PyYAML ; extra == 'typing'
Requires-Dist: types-setuptools ; extra == 'typing'
Requires-Dist: types-python-dateutil ; extra == 'typing'
Requires-Dist: types-mock ; extra == 'typing'
Requires-Dist: types-requests ; extra == 'typing'
Provides-Extra: xgboost
Requires-Dist: scikit-learn >=1.2.1 ; extra == 'xgboost'
Requires-Dist: xgboost <2.0.0 ; extra == 'xgboost'
